serius/__init__.py
serius/serius.py
serius/thread/__init__.py
serius/thread/timer/__init__.py
serius/thread/timer/repeatedTimer.py
serius/watcher/__init__.py
serius/watcher/dockerWatcher.py
serius/watcher/rancherWatcher.py
serius-1.2.1.dist-info/DESCRIPTION.rst
serius-1.2.1.dist-info/METADATA
serius-1.2.1.dist-info/RECORD
serius-1.2.1.dist-info/WHEEL
serius-1.2.1.dist-info/entry_points.txt
serius-1.2.1.dist-info/metadata.json
serius-1.2.1.dist-info/top_level.txt
