Metadata-Version: 2.0
Name: serius
Version: 1.2.1
Summary: Microservice Docker DNS for Local Linux
Home-page: https://github.com/MOXGA-OSS/gamer-serius
Author: GAMER
Author-email: UNKNOWN
License: UNKNOWN
Keywords: dns docker python microservices
Platform: UNKNOWN
Requires-Dist: docker
Requires-Dist: pathlib
